{
  "metadata": {
    "name": "demo"
  },
  "spec": {
    "displayName": "Quick starts demo",
    "durationMinutes": 5,
    "icon": "",
    "description": "This demo will walk you through quick start features",
    "introduction": "<h3>This demo will walk you through quick start features</h3>",
    "tasks": [
      {
        "title": "Highlighting (yaml+markdown)",
        "description": "<h2>Test</h2>\n<p>Hello world",
        "review": {
          "instructions": "<h4>To verify:</h4>\n<p>Did you see the elements highlighted?",
          "failedTaskHelp": "This task isn’t verified yet. Try the task again."
        },
        "summary": {
          "success": "You have learned about highlighting elements!",
          "failed": "Try the steps again."
        }
      }
    ],
    "conclusion": "You have finished the quick starts features overview"
  }
}